pca/__init__.py
pca/examples.py
pca/pca.py
pca/data/__init__.py
pca/tests/__init__.py
pca/tests/test_pca.py
pca-2.0.9.dist-info/LICENSE
pca-2.0.9.dist-info/METADATA
pca-2.0.9.dist-info/WHEEL
pca-2.0.9.dist-info/top_level.txt
pca-2.0.9.dist-info/RECORD
