Metadata-Version: 2.1
Name: pca
Version: 2.0.9
Summary: pca: A Python Package for Principal Component Analysis.
Home-page: https://erdogant.github.io/pca
Download-URL: https://github.com/erdogant/pca/archive/2.0.9.tar.gz
Author: Erdogan Taskesen
Author-email: erdogant@gmail.com
Classifier: Programming Language :: Python :: 3
Classifier: License :: OSI Approved :: MIT License
Classifier: Operating System :: OS Independent
Requires-Python: >=3
License-File: LICENSE
Requires-Dist: datazets
Requires-Dist: statsmodels
Requires-Dist: matplotlib
Requires-Dist: numpy
Requires-Dist: scikit-learn
Requires-Dist: scipy
Requires-Dist: colourmap>=1.1.19
Requires-Dist: pandas
Requires-Dist: scatterd>=1.3.7
Requires-Dist: adjusttext
